airflow_providers_rdb_to_parquet/__init__.py
airflow_providers_rdb_to_parquet/sql_to_s3_parquet_operator.py
airflow_providers_rdb_to_parquet-1.0.0.dist-info/METADATA
airflow_providers_rdb_to_parquet-1.0.0.dist-info/WHEEL
airflow_providers_rdb_to_parquet-1.0.0.dist-info/top_level.txt
airflow_providers_rdb_to_parquet-1.0.0.dist-info/RECORD
