Metadata-Version: 2.1
Name: airflow-providers-rdb-to-parquet
Version: 1.0.0
Summary: Custom Airflow Operator to extract data from PostgreSQL, convert it to Parquet format, and upload to S3.
Home-page: UNKNOWN
Author: Hazel Liu
Author-email: hazel.liu@crypto.com
License: UNKNOWN
Platform: UNKNOWN
Classifier: Programming Language :: Python :: 3
Classifier: Framework :: Apache Airflow
Classifier: License :: OSI Approved :: MIT License
Requires-Dist: pandas
Requires-Dist: pyarrow
Requires-Dist: apache-airflow
Requires-Dist: boto3
